Metadata-Version: 2.1
Name: TuneCoach
Version: 1.0.1
Summary: An interactive tool for practicing intonation
Home-page: https://github.com/bhostetler18/TuneCoach/
Author: Jamm Hostetler , James Eschrich, Joe Gravelle, Jenny Baik, Gavin Gui
Author-email: jeschrich@ufl.edu
License: UNKNOWN
Platform: UNKNOWN
Classifier: Programming Language :: Python :: 3
Classifier: Operating System :: POSIX :: Linux
Requires-Python: >=3.8
